razer_analog/__init__.py
razer_analog/driver.py
razer_analog/hidraw.py
razer_analog/hidrawtests.py
razer_analog/layout.py
razer_analog/mouse.py
razer_analog/razer_huntsman_mini_analog.json
razer_analog/razerctl.py
razer_analog-0.1.4.dist-info/METADATA
razer_analog-0.1.4.dist-info/WHEEL
razer_analog-0.1.4.dist-info/entry_points.txt
razer_analog-0.1.4.dist-info/RECORD
